mtcli_risco/__init__.py
mtcli_risco/commands/__init__.py
mtcli_risco/commands/checar.py
mtcli_risco/commands/monitorar.py
mtcli_risco/commands/trades.py
mtcli_risco/conf.py
mtcli_risco/models/__init__.py
mtcli_risco/models/checar_model.py
mtcli_risco/models/trades_model.py
mtcli_risco/mt5_context.py
mtcli_risco/plugin.py
mtcli_risco-2.2.2.dist-info/entry_points.txt
mtcli_risco-2.2.2.dist-info/LICENSE
mtcli_risco-2.2.2.dist-info/METADATA
mtcli_risco-2.2.2.dist-info/WHEEL
mtcli_risco-2.2.2.dist-info/RECORD
