Metadata-Version: 2.3
Name: mtcli-risco
Version: 2.2.2
Summary: Plugin mtcli para controle de loss diário
License: GPL-3.0
Author: Valmir França da Silva
Author-email: vfranca3@gmail.com
Requires-Python: >=3.10,<3.14
Classifier: License :: OSI Approved :: GNU General Public License v3 (GPLv3)
Classifier: Programming Language :: Python :: 3
Classifier: Programming Language :: Python :: 3.10
Classifier: Programming Language :: Python :: 3.11
Classifier: Programming Language :: Python :: 3.12
Classifier: Programming Language :: Python :: 3.13
Requires-Dist: mtcli (>=1.18.1)
Project-URL: Documentation, https://mtcli-risco.readthedocs.io
Project-URL: Homepage, https://github.com/vfranca/mtcli-risco
Project-URL: Repository, https://github.com/vfranca/mtcli-risco
Project-URL: issues, https://github.com/vfranca/mtcli-risco/issues
